{"id": "c9ef242447da214d3ca8dd3", "first_name": "Ethan", "last_name": "Brown", "ssn": "310-44-4361", "account_id": "", "wm_service_used": "robo_advisor", "gender": "F", "age": 48, "marital_status": "Widowed", "education_level": "secondary", "address": "97058 Felicia Turnpike\nJillianchester, OK 29800", "fa_id": "", "annual_revenue": 216326, "fund_id": "F-102", "asset_class": "Fixed Income Portfolio", "fund_performance": "f_102_performance", "funding_holding": "f_102_fund_holdings", "recommended_fund_id": "F-101", "contact_created_at": "2023-11-05T21:48:04.727450", "contact_modified_at": "2023-11-05T21:48:04.727464"}